cal_pystats/__init__.py
cal_pystats/__main__.py
cal_pystats/cli.py
cal_pystats/output.py
cal_pystats/scanner.py
cal_pystats-0.2.0.dist-info/METADATA
cal_pystats-0.2.0.dist-info/WHEEL
cal_pystats-0.2.0.dist-info/entry_points.txt
cal_pystats-0.2.0.dist-info/licenses/LICENSE
cal_pystats-0.2.0.dist-info/RECORD
