Metadata-Version: 2.4
Name: cal-pystats
Version: 0.2.0
Summary: A simple CLI tool to analyse Python file statistics in a directory
Project-URL: Repository, https://gitlab.com/cyberassessmentlabs/public/tools/cal-pystats
Project-URL: Documentation, https://cyberassessmentlabs.gitlab.io/public/docs/cal-pystats/latest/
Author: Cyber Assessment Labs
License-Expression: MIT
License-File: LICENSE
Keywords: cli,code-analysis,metrics,python,statistics
Classifier: Development Status :: 4 - Beta
Classifier: Environment :: Console
Classifier: Intended Audience :: Developers
Classifier: License :: OSI Approved :: MIT License
Classifier: Operating System :: OS Independent
Classifier: Programming Language :: Python :: 3
Classifier: Programming Language :: Python :: 3.14
Requires-Python: >=3.14
